topsis_raiza_102303068/__init__.py
topsis_raiza_102303068/topsis.py
topsis_raiza_102303068-1.0.0.dist-info/licenses/LICENSE
topsis_raiza_102303068-1.0.0.dist-info/METADATA
topsis_raiza_102303068-1.0.0.dist-info/WHEEL
topsis_raiza_102303068-1.0.0.dist-info/entry_points.txt
topsis_raiza_102303068-1.0.0.dist-info/top_level.txt
topsis_raiza_102303068-1.0.0.dist-info/RECORD
